{"status":"done","publicPath":"/","chunks":{"about":[{"name":"about.js","publicPath":"/about.js","path":"/home/hungnv/Projects/stock_dashboard_web_app/dist/about.js"}],"app":[{"name":"app.js","publicPath":"/app.js","path":"/home/hungnv/Projects/stock_dashboard_web_app/dist/app.js"}]},"error":"ModuleError","message":"Module Error (from ./node_modules/vue-loader/lib/loaders/templateLoader.js):\n(Emitted value instead of an instance of Error) \n\n  Errors compiling template:\n\n  tag <h4> has no matching end tag.\n\n  7  |            <div class=\"row\">\n  8  |              <div class=\"col-sm-5\">\n  9  |                <h4 class=\"card-title mb-0\">Traffic /h4>\n     |                ^^^^^^^^^^^^^^^^^^^^^^^^^^^^\n  10 |              </div>\n  11 |              <!-- /.col-->\n"}